cnrgh_dl/__init__.py
cnrgh_dl/__main__.py
cnrgh_dl/args.py
cnrgh_dl/auth/__init__.py
cnrgh_dl/auth/device_flow.py
cnrgh_dl/auth/refresh_token.py
cnrgh_dl/auth/token_manager.py
cnrgh_dl/config.py
cnrgh_dl/daemon.py
cnrgh_dl/download/__init__.py
cnrgh_dl/download/downloader.py
cnrgh_dl/download/integrity.py
cnrgh_dl/download/queue.py
cnrgh_dl/download/url.py
cnrgh_dl/exceptions.py
cnrgh_dl/exit.py
cnrgh_dl/instance.py
cnrgh_dl/logger.py
cnrgh_dl/models.py
cnrgh_dl/utils.py
cnrgh_dl-1.1.1.dist-info/METADATA
cnrgh_dl-1.1.1.dist-info/WHEEL
cnrgh_dl-1.1.1.dist-info/entry_points.txt
cnrgh_dl-1.1.1.dist-info/RECORD
