Metadata-Version: 2.3
Name: cnrgh-dl
Version: 1.1.1
Summary: Client de téléchargement compatible avec l'authentification à double facteur (2FA) requise par le portail de téléchargement du CNRGH.
License: CECILL-2.1
Keywords: CNRGH,download,projects,client,2FA
Author: Maxime Blanchon
Author-email: maxime.blanchon@cnrgh.fr
Requires-Python: >=3.9
Classifier: Development Status :: 5 - Production/Stable
Classifier: Intended Audience :: Science/Research
Classifier: License :: OSI Approved :: CEA CNRS Inria Logiciel Libre License, version 2.1 (CeCILL-2.1)
Classifier: Programming Language :: Python :: 3
Classifier: Programming Language :: Python :: 3.9
Classifier: Programming Language :: Python :: 3.10
Classifier: Programming Language :: Python :: 3.11
Classifier: Programming Language :: Python :: 3.12
Classifier: Programming Language :: Python :: 3.13
Requires-Dist: colorlog (>=6.8.2,<7.0.0)
Requires-Dist: environs (>=11.0.0,<12.0.0)
Requires-Dist: marshmallow (>=3.22.0,<4.0.0)
Requires-Dist: packaging (>=24.1,<25.0)
Requires-Dist: platformdirs (>=4.3.6,<5.0.0)
Requires-Dist: psutil (>=7.0.0,<8.0.0)
Requires-Dist: pydantic (>=2.9.2,<3.0.0)
Requires-Dist: requests (>=2.29.0,<2.30.0)
Requires-Dist: tqdm (>=4.66.5,<5.0.0)
Requires-Dist: typing-extensions (>=4.12.2,<5.0.0)
Requires-Dist: urllib3 (>=1.26.20,<2.0.0)
Project-URL: Changelog, https://www.cnrgh.fr/data-userdoc/download_with_client/#changelog
Project-URL: Documentation, https://www.cnrgh.fr/data-userdoc/download_with_client/
